openi/__init__.py
openi/_dataclass.py
openi/_exceptions.py
openi/_file.py
openi/_login.py
openi/_session.py
openi/_tqdm.py
openi/api.py
openi/constants.py
openi/downloader.py
openi/log.py
openi/uploader.py
openi/utils.py
openi/adaptor/__init__.py
openi/adaptor/om_hub/__init__.py
openi/adaptor/om_hub/download.py
openi/adaptor/om_hub/file_manager.py
openi/adaptor/om_hub/upload.py
openi/adaptor/om_hub/utils.py
openi/commands/__init__.py
openi/commands/dataset.py
openi/commands/dataset_deprecated.py
openi/commands/model.py
openi/commands/openi_cli.py
openi/commands/user.py
openi/refactor/__init__.py
openi/refactor/api.py
openi/refactor/constants.py
openi/refactor/sdk.py
openi/refactor/core/__init__.py
openi/refactor/core/auth.py
openi/refactor/core/dataclass.py
openi/refactor/core/router.py
openi/refactor/core/session.py
openi/refactor/plugins/__init__.py
openi/refactor/plugins/errors.py
openi/refactor/plugins/log.py
openi/refactor/plugins/progress.py
openi/refactor/service/__init__.py
openi/refactor/service/downloader.py
openi/refactor/service/file_manager.py
openi/refactor/service/notification.py
openi/refactor/service/uploader.py
openi/refactor/service/validators.py
openi/refactor/utils/__init__.py
openi/refactor/utils/deprecate.py
openi/refactor/utils/utils.py
openi-3.0.0.dist-info/METADATA
openi-3.0.0.dist-info/WHEEL
openi-3.0.0.dist-info/entry_points.txt
openi-3.0.0.dist-info/top_level.txt
openi-3.0.0.dist-info/RECORD
