Metadata-Version: 2.1
Name: openi
Version: 3.0.0
Summary: A package for openi pypi
Home-page: https://openi.pcl.ac.cn/OpenIOSSG/openi-pypi
Author: chenzh05
Author-email: chenzh.ds@outlook.com
License: MIT
Classifier: License :: OSI Approved :: MIT License
Classifier: Intended Audience :: Developers
Classifier: Topic :: Software Development :: Build Tools
Classifier: Programming Language :: Python :: 3.8
Classifier: Operating System :: OS Independent
Requires-Python: >=3.8
Requires-Dist: requests
Requires-Dist: tqdm
Requires-Dist: deprecated
Requires-Dist: pwinput
Requires-Dist: httpx
Requires-Dist: rich
Requires-Dist: aiofiles
Requires-Dist: h2
